eir/__init__.py
eir/build_module.py
eir/predict.py
eir/serve.py
eir/train.py
eir/data_load/__init__.py
eir/data_load/data_augmentation.py
eir/data_load/data_loading_funcs.py
eir/data_load/data_utils.py
eir/data_load/datasets.py
eir/data_load/label_setup.py
eir/data_load/storage_engine.py
eir/data_load/data_preparation_modules/__init__.py
eir/data_load/data_preparation_modules/common.py
eir/data_load/data_preparation_modules/imputation.py
eir/data_load/data_preparation_modules/input_preparation_wrappers.py
eir/data_load/data_preparation_modules/output_preparation_wrappers.py
eir/data_load/data_preparation_modules/prepare_array.py
eir/data_load/data_preparation_modules/prepare_bytes.py
eir/data_load/data_preparation_modules/prepare_image.py
eir/data_load/data_preparation_modules/prepare_omics.py
eir/data_load/data_preparation_modules/prepare_sequence.py
eir/data_load/data_preparation_modules/prepare_tabular.py
eir/data_load/data_source_modules/__init__.py
eir/data_load/data_source_modules/local_ops.py
eir/data_load/data_streaming/__init__.py
eir/data_load/data_streaming/streaming_dataset.py
eir/data_load/data_streaming/streaming_dataset_utils.py
eir/experiment_io/__init__.py
eir/experiment_io/configs_io.py
eir/experiment_io/experiment_io.py
eir/experiment_io/hooks_io.py
eir/experiment_io/input_object_io.py
eir/experiment_io/io_utils.py
eir/experiment_io/label_transformer_io.py
eir/experiment_io/metrics_io.py
eir/experiment_io/output_object_io.py
eir/experiment_io/input_object_io_modules/__init__.py
eir/experiment_io/input_object_io_modules/array_input_io.py
eir/experiment_io/input_object_io_modules/bytes_input_io.py
eir/experiment_io/input_object_io_modules/image_input_io.py
eir/experiment_io/input_object_io_modules/input_io_utils.py
eir/experiment_io/input_object_io_modules/omics_input_io.py
eir/experiment_io/input_object_io_modules/sequence_input_io.py
eir/experiment_io/output_object_io_modules/__init__.py
eir_dl-0.23.0.dist-info/METADATA
eir_dl-0.23.0.dist-info/WHEEL
eir_dl-0.23.0.dist-info/entry_points.txt
eir_dl-0.23.0.dist-info/licenses/LICENSE
eir_dl-0.23.0.dist-info/licenses/NOTICE
eir_dl-0.23.0.dist-info/RECORD
