Metadata-Version: 2.4
Name: eir-dl
Version: 0.23.0
Summary: Deep learning framework for genomics and multi-modal data
Project-URL: repository, https://github.com/arnor-sigurdsson/EIR
Author: Arnór Ingi Sigurðsson
License: Apache-2.0
License-File: LICENSE
License-File: NOTICE
Requires-Python: <3.14,>=3.13.0
Requires-Dist: adabelief-pytorch>=0.2.0
Requires-Dist: aislib>=0.3.0
Requires-Dist: captum>=0.7.0
Requires-Dist: colorama>=0.4.4
Requires-Dist: configargparse>=1.7
Requires-Dist: datasets>=3.2.0
Requires-Dist: diffusers>=0.33.1
Requires-Dist: einops>=0.8.0
Requires-Dist: fastapi>=0.115.4
Requires-Dist: ipython>=8.29.0
Requires-Dist: lifelines>=0.30.0
Requires-Dist: lightning>=2.5.0.post0
Requires-Dist: matplotlib>=3.9.0
Requires-Dist: numpy>=2.3.0
Requires-Dist: pandas>=2.2.2
Requires-Dist: pillow>=11.0.0
Requires-Dist: polars>=1.27.0
Requires-Dist: pyarrow>=18.0.0
Requires-Dist: pydantic>=2.9.2
Requires-Dist: pyyaml>=6.0.2
Requires-Dist: scikit-learn>=1.5.1
Requires-Dist: seaborn>=0.13.0
Requires-Dist: starlette>=0.41.2
Requires-Dist: sympy>=1.12.1
Requires-Dist: termcolor>=2.4.0
Requires-Dist: timm>=1.0.7
Requires-Dist: tokenizers>=0.21.0
Requires-Dist: torch-optimizer>=0.3.0
Requires-Dist: torch>=2.8.0
Requires-Dist: torchsurv>=0.1.4
Requires-Dist: torchview>=0.2.6
Requires-Dist: torchvision>=0.21.0
Requires-Dist: tqdm>=4.66.4
Requires-Dist: transformers>=4.53.2
Requires-Dist: uvicorn>=0.32.0
Requires-Dist: websocket-client>=1.8.0
Requires-Dist: websockets>=14.0
